LICENSE
MANIFEST.in
README.rst
requirements.txt
setup.py
feincms_pagepermissions.egg-info/PKG-INFO
feincms_pagepermissions.egg-info/SOURCES.txt
feincms_pagepermissions.egg-info/dependency_links.txt
feincms_pagepermissions.egg-info/requires.txt
feincms_pagepermissions.egg-info/top_level.txt
pagepermissions/__init__.py
pagepermissions/extension.py
pagepermissions/templatetags/__init__.py
pagepermissions/templatetags/feincms_pagepermissions_tags.py