Metadata-Version: 1.1
Name: feincms-pagepermissions
Version: 0.3.0
Summary: A simple FeinCMS extension that adds permission-checking to a model.
Home-page: https://github.com/ebrelsford/feincms-pagepermissions/
Author: Eric Brelsford
Author-email: ebrelsford@gmail.com
License: BSD License
Platform: OS Independent
Classifier: Development Status :: 4 - Beta
Classifier: Environment :: Web Environment
Classifier: Framework :: Django
Classifier: Intended Audience :: Developers
Classifier: License :: OSI Approved :: BSD License
Classifier: Operating System :: OS Independent
Classifier: Programming Language :: Python
Classifier: Topic :: Internet :: WWW/HTTP :: Dynamic Content
Classifier: Topic :: Software Development
